{
  "elo": {
    "Argentina": 2166.69,
    "France": 2178.81,
    "Spain": 2211.98,
    "Brazil": 1997.94,
    "England": 2039.47,
    "Belgium": 1881.71,
    "Portugal": 1875.73,
    "Netherlands": 1910.49,
    "Germany": 2032.47,
    "Italy": 1790.17,
    "Croatia": 1817.67,
    "Uruguay": 1745.12,
    "Denmark": 1737.73,
    "Mexico": 1872.95,
    "Colombia": 1962.77,
    "Senegal": 1857.06,
    "Morocco": 1926.86,
    "Switzerland": 1913.2,
    "USA": 1897.45,
    "Japan": 1928.08,
    "South Korea": 1803.82,
    "Ecuador": 1782.38,
    "Chile": 1619.16,
    "Peru": 1613.94,
    "Iran": 1815.89,
    "Australia": 1779.68,
    "Norway": 1994.09,
    "Poland": 1662.91,
    "Turkey": 1749.11,
    "Austria": 1816.78,
    "Algeria": 1783.76,
    "Sweden": 1720.12,
    "Egypt": 1797.74,
    "Nigeria": 1838.4,
    "Cameroon": 1679.28,
    "Saudi Arabia": 1592.74,
    "Serbia": 1487.25,
    "Ghana": 1650.75,
    "Tunisia": 1534.32,
    "Paraguay": 1770.34,
    "Scotland": 1583.53,
    "Qatar": 1547.43,
    "South Africa": 1554.93,
    "Ivory Coast": 1814.93,
    "Venezuela": 1587.47,
    "Costa Rica": 1542.59,
    "Panama": 1477.68,
    "Bolivia": 1543.74,
    "Wales": 1628.19,
    "Bosnia": 1618.63,
    "Slovakia": 1555.67,
    "Greece": 1542.48,
    "Georgia": 1550.7,
    "Ukraine": 1606.79,
    "Romania": 1460.06,
    "Hungary": 1552.85,
    "Canada": 1703.67,
    "New Zealand": 1370.67,
    "Iraq": 1552.85,
    "Jordan": 1471.94,
    "Uzbekistan": 1475.72,
    "DR Congo": 1630.88,
    "Haiti": 1308.77,
    "Cape Verde": 1586.37,
    "Curacao": 1393.02,
    "Albania": 1538.6,
    "Czechia": 1607.55,
    "Slovenia": 1563.51,
    "Israel": 1510.86,
    "China": 1453.62,
    "Indonesia": 1477.32,
    "Bahrain": 1289.95,
    "Jamaica": 1411.46,
    "Vietnam": 1339.96,
    "Tanzania": 1472.0,
    "Sao Tome": 1482.72,
    "Mauritania": 1473.93,
    "Ethiopia": 1488.95,
    "Liberia": 1496.41,
    "Lebanon": 1457.01,
    "Guinea Bissau": 1450.92,
    "India": 1485.44,
    "Mozambique": 1466.97,
    "Gambia": 1476.5,
    "Equatorial Guinea": 1397.46,
    "Congo": 1520.98,
    "UAE": 1523.0,
    "Zambia": 1475.82,
    "Syria": 1479.75,
    "Angola": 1471.93,
    "Congo DR": 1494.48,
    "Mali": 1514.76,
    "North Korea": 1397.01,
    "Thailand": 1487.8,
    "Hong Kong": 1492.24,
    "El Salvador": 1491.11,
    "Singapore": 1488.53,
    "Benin": 1465.99,
    "Myanmar": 1493.24,
    "Ireland": 1666.66,
    "Gabon": 1377.31,
    "Burkina Faso": 1544.56,
    "Palestine": 1518.16,
    "Finland": 1593.46,
    "Central African Rep": 1493.25,
    "Libya": 1515.95,
    "Kyrgyzstan": 1470.83,
    "Uganda": 1442.42,
    "Botswana": 1391.53,
    "Moldova": 1443.03,
    "Lithuania": 1485.36,
    "Malta": 1432.01,
    "Faroe Islands": 1465.11,
    "Kazakhstan": 1492.57,
    "Estonia": 1374.0,
    "Montenegro": 1499.94,
    "Gibraltar": 1459.69,
    "Latvia": 1497.22,
    "Kuwait": 1453.87,
    "Andorra": 1446.21,
    "Oman": 1405.44,
    "Liechtenstein": 1457.26,
    "San Marino": 1464.63,
    "Cyprus": 1441.96,
    "Bulgaria": 1468.53,
    "Luxembourg": 1423.89,
    "Northern Ireland": 1547.6,
    "Azerbaijan": 1426.3,
    "North Macedonia": 1501.27,
    "Belarus": 1532.99,
    "Iceland": 1491.73,
    "Dominican Republic": 1442.94,
    "Armenia": 1415.29,
    "Puerto Rico": 1497.45,
    "Comoros": 1493.31,
    "Zimbabwe": 1436.27,
    "Sudan": 1463.78,
    "Kosovo": 1526.96,
    "Burundi": 1489.58,
    "Russia": 1489.83,
    "Nicaragua": 1503.82,
    "Trinidad and Tobago": 1485.85,
    "Madagascar": 1490.13,
    "Aruba": 1421.27,
    "Honduras": 1497.67,
    "Guatemala": 1490.03
  },
  "dc": {
    "attack": {
      "Albania": 0.10965015537225827,
      "Algeria": 0.1217842547809726,
      "Andorra": -1.3529496000356984,
      "Angola": -0.5078467511212709,
      "Argentina": 1.048696731494636,
      "Armenia": -0.846075997644248,
      "Aruba": -1.0547224758974134,
      "Australia": 0.2225346553472993,
      "Austria": 0.8456183954706677,
      "Azerbaijan": -0.7944868250528763,
      "Bahrain": -0.7168828396729549,
      "Belarus": 0.4709154675378353,
      "Belgium": 0.15990535406425258,
      "Benin": -0.3289295027709253,
      "Bolivia": -0.06606467933857635,
      "Bosnia": 0.1483817583393785,
      "Botswana": -1.722642368750808,
      "Brazil": 0.9959102773257781,
      "Bulgaria": -0.5322563502123386,
      "Burkina Faso": -0.29561251791535126,
      "Burundi": -0.3416225783403413,
      "Cameroon": 0.21052027267292892,
      "Canada": 0.7136846199377787,
      "Cape Verde": 0.9767291017115902,
      "Central African Rep": -0.3860822935398431,
      "Chile": -0.2697160042172561,
      "China": -0.4776646245877822,
      "Colombia": 0.9121680222365767,
      "Comoros": -1.656843386896615,
      "Congo": 0.5598156106029715,
      "Congo DR": -0.18300113278014574,
      "Costa Rica": 0.18267738228422442,
      "Croatia": 0.880802435116013,
      "Curacao": 0.29135402636655056,
      "Cyprus": -0.5275654579778591,
      "Czechia": 0.3224916621542781,
      "DR Congo": 0.2407424931656514,
      "Denmark": 0.47786354850607704,
      "Dominican Republic": 0.09954413503047892,
      "Ecuador": -0.2602352362309161,
      "Egypt": 0.5516100762068094,
      "El Salvador": -0.7817856405069481,
      "England": 0.8552844059488875,
      "Equatorial Guinea": -0.44217983654934806,
      "Estonia": -0.19313870178774326,
      "Ethiopia": -0.44573513272438486,
      "Faroe Islands": 0.11077017456526626,
      "Finland": -0.0408259126210021,
      "France": 0.998165381529864,
      "Gabon": 0.1008959884667495,
      "Gambia": -0.2236351131532917,
      "Georgia": 0.5001850436412563,
      "Germany": 1.126656954344791,
      "Ghana": 0.2616748778936751,
      "Gibraltar": -0.564553933302543,
      "Greece": 0.5667695190396413,
      "Guatemala": -0.36689040319281235,
      "Guinea Bissau": -0.7978752066925114,
      "Haiti": -1.7238991383951785,
      "Honduras": -0.2854995701750165,
      "Hong Kong": -0.6349565263139402,
      "Hungary": -0.26438661353801823,
      "Iceland": 0.1949054407058413,
      "India": -0.47937251054137336,
      "Indonesia": -0.10108595593929165,
      "Iran": 0.5942860681609179,
      "Iraq": -0.26231458062285207,
      "Ireland": 0.5668725597110882,
      "Israel": 0.626420820852844,
      "Italy": 0.7029386182800165,
      "Ivory Coast": 0.699015723228683,
      "Jamaica": 0.1649686372287476,
      "Japan": 0.8343234290312731,
      "Jordan": 0.12887080354382638,
      "Kazakhstan": 0.12659622233180984,
      "Kosovo": 0.7764188587484994,
      "Kuwait": -0.5961719854954974,
      "Kyrgyzstan": 0.20602740094425062,
      "Latvia": -0.5667799495291832,
      "Lebanon": -0.8645906130100314,
      "Liberia": -0.28209652455670037,
      "Libya": -0.5179370910694012,
      "Liechtenstein": -1.1307282804916747,
      "Lithuania": -0.8541328128587372,
      "Luxembourg": -0.5947864076899024,
      "Madagascar": -0.3438843087883024,
      "Mali": -0.42142822441661787,
      "Malta": -1.5458779212485811,
      "Mauritania": 0.21567901447877236,
      "Mexico": 0.21424569107132455,
      "Moldova": -0.6766295522085494,
      "Montenegro": -0.24481777681251604,
      "Morocco": 0.44697780004954246,
      "Mozambique": 0.1330269875439462,
      "Myanmar": -0.5098686064305108,
      "Netherlands": 1.091651131435609,
      "New Zealand": 0.5998398132951805,
      "Nicaragua": -0.7106773329473908,
      "Nigeria": 0.4492849754786796,
      "North Korea": -0.491092691302966,
      "North Macedonia": -1.4467753226312867,
      "Northern Ireland": 0.185041818950987,
      "Norway": 1.2155680629345862,
      "Oman": -1.5560153974151567,
      "Palestine": -0.2218313821695333,
      "Panama": 0.24094945150175878,
      "Paraguay": 0.48246660101536526,
      "Peru": -0.7450793193193118,
      "Poland": 0.4705746394657528,
      "Portugal": 0.9371639864857491,
      "Puerto Rico": -0.2252067442624165,
      "Qatar": 0.005419585119973182,
      "Romania": -0.35206308844948025,
      "Russia": -0.6072614702051232,
      "San Marino": -1.3440576130548412,
      "Sao Tome": -0.38749859314672164,
      "Saudi Arabia": 0.023376259827780375,
      "Scotland": 0.3385465132267914,
      "Senegal": 0.7745810247792055,
      "Serbia": 0.00930223425501501,
      "Singapore": -0.6895992254324147,
      "Slovakia": 0.47083116867864366,
      "Slovenia": -0.10063880791254716,
      "South Africa": 0.2536200265692397,
      "South Korea": 0.5918288614639028,
      "Spain": 0.9166213119643061,
      "Sudan": -0.7383959417240507,
      "Sweden": 0.877158442374742,
      "Switzerland": 0.7351268753269623,
      "Syria": -0.10316229630230685,
      "Tanzania": -0.37894756838750554,
      "Thailand": -0.6504940160252631,
      "Trinidad and Tobago": -0.6897251520061077,
      "Tunisia": 0.022973234621309995,
      "Turkey": 0.41736526781069294,
      "UAE": 0.38886614633531896,
      "USA": 1.1419316515973432,
      "Uganda": -0.1574614658781615,
      "Ukraine": 0.33010385060168146,
      "Uruguay": 0.43000612006261857,
      "Uzbekistan": 0.21289491654542156,
      "Venezuela": 0.4237768424484294,
      "Vietnam": 0.5546671821465989,
      "Wales": -0.11355020532658755,
      "Zambia": -0.6206082554831728,
      "Zimbabwe": 0.5416751365798714
    },
    "defense": {
      "Albania": -0.2756558021011598,
      "Algeria": -0.4530314871025329,
      "Andorra": 0.29653811047206996,
      "Angola": -0.41362479406679054,
      "Argentina": -1.4581708331451781,
      "Armenia": 0.8208850383601061,
      "Aruba": 0.9394710385816727,
      "Australia": -0.555867908724626,
      "Austria": -0.4534433909389253,
      "Azerbaijan": 0.06281596380328604,
      "Bahrain": 0.47056733452836835,
      "Belarus": 0.49761589606088774,
      "Belgium": -0.8555417169286325,
      "Benin": 0.21441432305532293,
      "Bolivia": -0.03335917628152968,
      "Bosnia": 0.10323623217387076,
      "Botswana": 0.44760736229685344,
      "Brazil": -0.6751682545024206,
      "Bulgaria": 0.46554345358598376,
      "Burkina Faso": 0.20018262484595165,
      "Burundi": 1.0259959497296454,
      "Cameroon": -0.2902877385643243,
      "Canada": -0.42936828146644895,
      "Cape Verde": -0.5219375615689356,
      "Central African Rep": 0.31250118259616483,
      "Chile": -0.37090374679883886,
      "China": 0.17054270500962643,
      "Colombia": -0.7052409388760759,
      "Comoros": -0.2716641499930524,
      "Congo": -0.3729157468510446,
      "Congo DR": -0.47145179274342347,
      "Costa Rica": 0.20044041392601472,
      "Croatia": -0.12186023019564625,
      "Curacao": 0.61778658271532,
      "Cyprus": 0.40058031334418287,
      "Czechia": -0.14607540416883352,
      "DR Congo": -0.9042794681602027,
      "Denmark": -0.3073783501571552,
      "Dominican Republic": 0.5952606554240394,
      "Ecuador": -1.127205969553281,
      "Egypt": -0.4988572077367459,
      "El Salvador": -0.2397921196852772,
      "England": -0.8516701400929304,
      "Equatorial Guinea": 0.7280258487535847,
      "Estonia": 0.11460375050911949,
      "Ethiopia": -0.09894645103343487,
      "Faroe Islands": -0.015883005947278563,
      "Finland": -0.17189058943526403,
      "France": -0.980137682647356,
      "Gabon": 0.3968735323460945,
      "Gambia": 0.3750878349535462,
      "Georgia": 0.1632300785919683,
      "Germany": -0.6411135905242884,
      "Ghana": -0.4054589165828614,
      "Gibraltar": 0.8194107441232641,
      "Greece": 0.10224664459032026,
      "Guatemala": 1.103640115124171,
      "Guinea Bissau": -0.00495503255231709,
      "Haiti": -0.025498130676697664,
      "Honduras": -0.2747036498102302,
      "Hong Kong": 0.8173217368861785,
      "Hungary": -0.03754983382209062,
      "Iceland": 0.36934740251732456,
      "India": 0.3371038992380607,
      "Indonesia": 0.20888323265199707,
      "Iran": -0.2039541251399535,
      "Iraq": -0.03641780023395831,
      "Ireland": -0.4921772107072411,
      "Israel": 0.25709952333952685,
      "Italy": -0.26111322822349187,
      "Ivory Coast": -0.42674234120366017,
      "Jamaica": 0.6112693010883358,
      "Japan": -0.652322727020066,
      "Jordan": 0.13597867964874016,
      "Kazakhstan": 0.32301884125630553,
      "Kosovo": 0.2540324568718431,
      "Kuwait": 0.3393714654523177,
      "Kyrgyzstan": 0.5811540324486376,
      "Latvia": -0.03453170937161455,
      "Lebanon": 0.85534378890649,
      "Liberia": 0.2888240425654382,
      "Libya": -1.174564500771234,
      "Liechtenstein": 1.3051584715593454,
      "Lithuania": -0.543476210288529,
      "Luxembourg": 0.05453483444276992,
      "Madagascar": 0.806635643652495,
      "Mali": -0.25368669514918896,
      "Malta": 0.47792341000162547,
      "Mauritania": -0.14183907873277293,
      "Mexico": -0.9146526454272008,
      "Moldova": 0.593207976188697,
      "Montenegro": 0.18826699392655713,
      "Morocco": -1.2086268810073237,
      "Mozambique": 0.3718039754424401,
      "Myanmar": 0.43716570501280394,
      "Netherlands": -0.423954576403422,
      "New Zealand": 0.230519979530604,
      "Nicaragua": -0.842367010883317,
      "Nigeria": -0.6970998089797316,
      "North Korea": 0.06861402382538602,
      "North Macedonia": 0.3444796638619845,
      "Northern Ireland": -0.41936160646670484,
      "Norway": -0.4568295211974105,
      "Oman": 0.5196387684416656,
      "Palestine": -0.2938369579262441,
      "Panama": 0.30092458597788463,
      "Paraguay": -0.4073604619623242,
      "Peru": -0.5822078331330752,
      "Poland": -0.2776505728255863,
      "Portugal": -0.5505976800125969,
      "Puerto Rico": 0.6494623041542887,
      "Qatar": 0.4203885778255929,
      "Romania": 0.0019542102633023878,
      "Russia": -0.3534444755819901,
      "San Marino": 0.8747428725277241,
      "Sao Tome": 0.9165676641243306,
      "Saudi Arabia": 0.03163954238010217,
      "Scotland": -0.17472803097054307,
      "Senegal": -0.3202051877271058,
      "Serbia": -0.18484441900956378,
      "Singapore": 0.9807583403432778,
      "Slovakia": -0.21921118369153117,
      "Slovenia": -0.8258627120487624,
      "South Africa": -0.03783379941186288,
      "South Korea": -0.16425392189492674,
      "Spain": -1.5930869805009,
      "Sudan": 0.4945604551745021,
      "Sweden": 0.2441521669324737,
      "Switzerland": -0.422664992993425,
      "Syria": 0.5586238176859195,
      "Tanzania": 0.1250697737609891,
      "Thailand": 0.1818476218575693,
      "Trinidad and Tobago": 0.8997680938083431,
      "Tunisia": 0.44340061978572914,
      "Turkey": -0.42551718358832175,
      "UAE": -0.16339502526839697,
      "USA": -0.3591944688893183,
      "Uganda": 0.6507777131884104,
      "Ukraine": 0.127372359818159,
      "Uruguay": -0.7434012668260817,
      "Uzbekistan": -0.024697916607089965,
      "Venezuela": 0.07244898749680376,
      "Vietnam": 0.7419382681045231,
      "Wales": -0.3152343456897555,
      "Zambia": 0.5167439861580813,
      "Zimbabwe": 0.4803791718134861
    },
    "home_adv": 0.2826950498974976,
    "rho": -0.13129178108285428,
    "teams": [
      "Albania",
      "Algeria",
      "Andorra",
      "Angola",
      "Argentina",
      "Armenia",
      "Aruba",
      "Australia",
      "Austria",
      "Azerbaijan",
      "Bahrain",
      "Belarus",
      "Belgium",
      "Benin",
      "Bolivia",
      "Bosnia",
      "Botswana",
      "Brazil",
      "Bulgaria",
      "Burkina Faso",
      "Burundi",
      "Cameroon",
      "Canada",
      "Cape Verde",
      "Central African Rep",
      "Chile",
      "China",
      "Colombia",
      "Comoros",
      "Congo",
      "Congo DR",
      "Costa Rica",
      "Croatia",
      "Curacao",
      "Cyprus",
      "Czechia",
      "DR Congo",
      "Denmark",
      "Dominican Republic",
      "Ecuador",
      "Egypt",
      "El Salvador",
      "England",
      "Equatorial Guinea",
      "Estonia",
      "Ethiopia",
      "Faroe Islands",
      "Finland",
      "France",
      "Gabon",
      "Gambia",
      "Georgia",
      "Germany",
      "Ghana",
      "Gibraltar",
      "Greece",
      "Guatemala",
      "Guinea Bissau",
      "Haiti",
      "Honduras",
      "Hong Kong",
      "Hungary",
      "Iceland",
      "India",
      "Indonesia",
      "Iran",
      "Iraq",
      "Ireland",
      "Israel",
      "Italy",
      "Ivory Coast",
      "Jamaica",
      "Japan",
      "Jordan",
      "Kazakhstan",
      "Kosovo",
      "Kuwait",
      "Kyrgyzstan",
      "Latvia",
      "Lebanon",
      "Liberia",
      "Libya",
      "Liechtenstein",
      "Lithuania",
      "Luxembourg",
      "Madagascar",
      "Mali",
      "Malta",
      "Mauritania",
      "Mexico",
      "Moldova",
      "Montenegro",
      "Morocco",
      "Mozambique",
      "Myanmar",
      "Netherlands",
      "New Zealand",
      "Nicaragua",
      "Nigeria",
      "North Korea",
      "North Macedonia",
      "Northern Ireland",
      "Norway",
      "Oman",
      "Palestine",
      "Panama",
      "Paraguay",
      "Peru",
      "Poland",
      "Portugal",
      "Puerto Rico",
      "Qatar",
      "Romania",
      "Russia",
      "San Marino",
      "Sao Tome",
      "Saudi Arabia",
      "Scotland",
      "Senegal",
      "Serbia",
      "Singapore",
      "Slovakia",
      "Slovenia",
      "South Africa",
      "South Korea",
      "Spain",
      "Sudan",
      "Sweden",
      "Switzerland",
      "Syria",
      "Tanzania",
      "Thailand",
      "Trinidad and Tobago",
      "Tunisia",
      "Turkey",
      "UAE",
      "USA",
      "Uganda",
      "Ukraine",
      "Uruguay",
      "Uzbekistan",
      "Venezuela",
      "Vietnam",
      "Wales",
      "Zambia",
      "Zimbabwe"
    ],
    "converged": true,
    "fun": 2252.093401193373
  }
}