{
  "Mexico": {
    "win": 0.034,
    "final": 0.0733,
    "sf": 0.1354,
    "qf": 0.2978,
    "win_lo": 0.0126,
    "win_hi": 0.0526,
    "win_delta": 0.0017
  },
  "South Africa": {
    "win": 0.0,
    "final": 0.0,
    "sf": 0.0,
    "qf": 0.0,
    "win_lo": 0.0,
    "win_hi": 0.0,
    "win_delta": -0.0023
  },
  "South Korea": {
    "win": 0.0,
    "final": 0.0,
    "sf": 0.0,
    "qf": 0.0,
    "win_lo": 0.0,
    "win_hi": 0.0,
    "win_delta": 0.0
  },
  "Czechia": {
    "win": 0.0,
    "final": 0.0,
    "sf": 0.0,
    "qf": 0.0,
    "win_lo": 0.0,
    "win_hi": 0.0,
    "win_delta": 0.0
  },
  "Canada": {
    "win": 0.0237,
    "final": 0.0567,
    "sf": 0.1601,
    "qf": 0.4332,
    "win_lo": 0.0074,
    "win_hi": 0.0425,
    "win_delta": 0.0043
  },
  "Switzerland": {
    "win": 0.0192,
    "final": 0.0522,
    "sf": 0.1239,
    "qf": 0.2537,
    "win_lo": 0.007,
    "win_hi": 0.0344,
    "win_delta": 0.0005
  },
  "Qatar": {
    "win": 0.0,
    "final": 0.0,
    "sf": 0.0,
    "qf": 0.0,
    "win_lo": 0.0,
    "win_hi": 0.0,
    "win_delta": 0.0
  },
  "Bosnia": {
    "win": 0.0006,
    "final": 0.0032,
    "sf": 0.0134,
    "qf": 0.0414,
    "win_lo": 0.0,
    "win_hi": 0.0024,
    "win_delta": 0.0
  },
  "Brazil": {
    "win": 0.0975,
    "final": 0.1775,
    "sf": 0.3839,
    "qf": 0.6297,
    "win_lo": 0.0669,
    "win_hi": 0.1444,
    "win_delta": 0.0315
  },
  "Morocco": {
    "win": 0.0477,
    "final": 0.1024,
    "sf": 0.2542,
    "qf": 0.5668,
    "win_lo": 0.0296,
    "win_hi": 0.0677,
    "win_delta": 0.0192
  },
  "Haiti": {
    "win": 0.0,
    "final": 0.0,
    "sf": 0.0,
    "qf": 0.0,
    "win_lo": 0.0,
    "win_hi": 0.0,
    "win_delta": 0.0
  },
  "Scotland": {
    "win": 0.0,
    "final": 0.0,
    "sf": 0.0,
    "qf": 0.0,
    "win_lo": 0.0,
    "win_hi": 0.0,
    "win_delta": 0.0
  },
  "USA": {
    "win": 0.0357,
    "final": 0.0961,
    "sf": 0.2304,
    "qf": 0.4397,
    "win_lo": 0.008,
    "win_hi": 0.0699,
    "win_delta": 0.0054
  },
  "Paraguay": {
    "win": 0.0246,
    "final": 0.069,
    "sf": 0.1627,
    "qf": 0.4657,
    "win_lo": 0.0114,
    "win_hi": 0.0397,
    "win_delta": 0.0179
  },
  "Australia": {
    "win": 0.0119,
    "final": 0.0285,
    "sf": 0.0684,
    "qf": 0.1823,
    "win_lo": 0.0024,
    "win_hi": 0.0229,
    "win_delta": 0.0018
  },
  "Turkey": {
    "win": 0.0,
    "final": 0.0,
    "sf": 0.0,
    "qf": 0.0,
    "win_lo": 0.0,
    "win_hi": 0.0,
    "win_delta": 0.0
  },
  "Germany": {
    "win": 0.0,
    "final": 0.0,
    "sf": 0.0,
    "qf": 0.0,
    "win_lo": 0.0,
    "win_hi": 0.0,
    "win_delta": -0.0467
  },
  "Curacao": {
    "win": 0.0,
    "final": 0.0,
    "sf": 0.0,
    "qf": 0.0,
    "win_lo": 0.0,
    "win_hi": 0.0,
    "win_delta": 0.0
  },
  "Ivory Coast": {
    "win": 0.0,
    "final": 0.0,
    "sf": 0.0,
    "qf": 0.0,
    "win_lo": 0.0,
    "win_hi": 0.0,
    "win_delta": -0.0147
  },
  "Ecuador": {
    "win": 0.0161,
    "final": 0.0419,
    "sf": 0.0925,
    "qf": 0.2365,
    "win_lo": 0.0086,
    "win_hi": 0.0263,
    "win_delta": -0.0005
  },
  "Netherlands": {
    "win": 0.0,
    "final": 0.0,
    "sf": 0.0,
    "qf": 0.0,
    "win_lo": 0.0,
    "win_hi": 0.0,
    "win_delta": -0.0259
  },
  "Japan": {
    "win": 0.0,
    "final": 0.0,
    "sf": 0.0,
    "qf": 0.0,
    "win_lo": 0.0,
    "win_hi": 0.0,
    "win_delta": -0.0135
  },
  "Sweden": {
    "win": 0.0021,
    "final": 0.0085,
    "sf": 0.0238,
    "qf": 0.0531,
    "win_lo": 0.0,
    "win_hi": 0.0056,
    "win_delta": 0.0002
  },
  "Tunisia": {
    "win": 0.0,
    "final": 0.0,
    "sf": 0.0,
    "qf": 0.0,
    "win_lo": 0.0,
    "win_hi": 0.0,
    "win_delta": 0.0
  },
  "Belgium": {
    "win": 0.0277,
    "final": 0.0683,
    "sf": 0.1532,
    "qf": 0.303,
    "win_lo": 0.0163,
    "win_hi": 0.0401,
    "win_delta": -0.0012
  },
  "Egypt": {
    "win": 0.0051,
    "final": 0.015,
    "sf": 0.0424,
    "qf": 0.1445,
    "win_lo": 0.0016,
    "win_hi": 0.0091,
    "win_delta": -0.0023
  },
  "Iran": {
    "win": 0.0,
    "final": 0.0,
    "sf": 0.0,
    "qf": 0.0,
    "win_lo": 0.0,
    "win_hi": 0.0,
    "win_delta": 0.0
  },
  "New Zealand": {
    "win": 0.0,
    "final": 0.0,
    "sf": 0.0,
    "qf": 0.0,
    "win_lo": 0.0,
    "win_hi": 0.0,
    "win_delta": 0.0
  },
  "Spain": {
    "win": 0.1395,
    "final": 0.2176,
    "sf": 0.3281,
    "qf": 0.5585,
    "win_lo": 0.0977,
    "win_hi": 0.1782,
    "win_delta": 0.0065
  },
  "Cape Verde": {
    "win": 0.0097,
    "final": 0.0227,
    "sf": 0.0526,
    "qf": 0.1383,
    "win_lo": 0.0,
    "win_hi": 0.0236,
    "win_delta": 0.0028
  },
  "Saudi Arabia": {
    "win": 0.0,
    "final": 0.0,
    "sf": 0.0,
    "qf": 0.0,
    "win_lo": 0.0,
    "win_hi": 0.0,
    "win_delta": 0.0
  },
  "Uruguay": {
    "win": 0.0,
    "final": 0.0,
    "sf": 0.0,
    "qf": 0.0,
    "win_lo": 0.0,
    "win_hi": 0.0,
    "win_delta": 0.0
  },
  "France": {
    "win": 0.1506,
    "final": 0.2688,
    "sf": 0.3867,
    "qf": 0.5735,
    "win_lo": 0.118,
    "win_hi": 0.185,
    "win_delta": 0.0074
  },
  "Senegal": {
    "win": 0.0206,
    "final": 0.056,
    "sf": 0.133,
    "qf": 0.2652,
    "win_lo": 0.0072,
    "win_hi": 0.0343,
    "win_delta": 0.0051
  },
  "Norway": {
    "win": 0.0343,
    "final": 0.0722,
    "sf": 0.2019,
    "qf": 0.3703,
    "win_lo": 0.0136,
    "win_hi": 0.0561,
    "win_delta": 0.0178
  },
  "Iraq": {
    "win": 0.0,
    "final": 0.0,
    "sf": 0.0,
    "qf": 0.0,
    "win_lo": 0.0,
    "win_hi": 0.0,
    "win_delta": 0.0
  },
  "Argentina": {
    "win": 0.1394,
    "final": 0.2125,
    "sf": 0.313,
    "qf": 0.5349,
    "win_lo": 0.0916,
    "win_hi": 0.1905,
    "win_delta": -0.0067
  },
  "Algeria": {
    "win": 0.0041,
    "final": 0.0154,
    "sf": 0.0486,
    "qf": 0.1472,
    "win_lo": 0.0008,
    "win_hi": 0.0073,
    "win_delta": -0.0002
  },
  "Austria": {
    "win": 0.0022,
    "final": 0.0064,
    "sf": 0.0199,
    "qf": 0.0615,
    "win_lo": 0.0,
    "win_hi": 0.0046,
    "win_delta": -0.0002
  },
  "Jordan": {
    "win": 0.0,
    "final": 0.0,
    "sf": 0.0,
    "qf": 0.0,
    "win_lo": 0.0,
    "win_hi": 0.0,
    "win_delta": 0.0
  },
  "Portugal": {
    "win": 0.0422,
    "final": 0.0785,
    "sf": 0.1464,
    "qf": 0.298,
    "win_lo": 0.0172,
    "win_hi": 0.0719,
    "win_delta": -0.0072
  },
  "DR Congo": {
    "win": 0.0059,
    "final": 0.0184,
    "sf": 0.0474,
    "qf": 0.1041,
    "win_lo": 0.0024,
    "win_hi": 0.0103,
    "win_delta": 0.0002
  },
  "Uzbekistan": {
    "win": 0.0,
    "final": 0.0,
    "sf": 0.0,
    "qf": 0.0,
    "win_lo": 0.0,
    "win_hi": 0.0,
    "win_delta": 0.0
  },
  "Colombia": {
    "win": 0.0573,
    "final": 0.1256,
    "sf": 0.2469,
    "qf": 0.4064,
    "win_lo": 0.0323,
    "win_hi": 0.0805,
    "win_delta": 0.0012
  },
  "England": {
    "win": 0.0388,
    "final": 0.085,
    "sf": 0.1515,
    "qf": 0.2693,
    "win_lo": 0.0267,
    "win_hi": 0.0514,
    "win_delta": -0.0009
  },
  "Croatia": {
    "win": 0.0035,
    "final": 0.01,
    "sf": 0.0291,
    "qf": 0.0819,
    "win_lo": 0.0008,
    "win_hi": 0.0065,
    "win_delta": -0.0016
  },
  "Ghana": {
    "win": 0.0061,
    "final": 0.0184,
    "sf": 0.0506,
    "qf": 0.1434,
    "win_lo": 0.0008,
    "win_hi": 0.0143,
    "win_delta": 0.0006
  },
  "Panama": {
    "win": 0.0,
    "final": 0.0,
    "sf": 0.0,
    "qf": 0.0,
    "win_lo": 0.0,
    "win_hi": 0.0,
    "win_delta": 0.0
  }
}