{
  "Mexico": {
    "win": 0.0022,
    "final": 0.0079,
    "sf": 0.0308,
    "qf": 0.1188,
    "win_lo": 0.0,
    "win_hi": 0.0049,
    "win_delta": 0.002
  },
  "South Africa": {
    "win": 0.0,
    "final": 0.0002,
    "sf": 0.001,
    "qf": 0.0079,
    "win_lo": 0.0,
    "win_hi": 0.0,
    "win_delta": -0.0016
  },
  "South Korea": {
    "win": 0.0031,
    "final": 0.0146,
    "sf": 0.0508,
    "qf": 0.1726,
    "win_lo": 0.0,
    "win_hi": 0.0104,
    "win_delta": -0.0023
  },
  "Czechia": {
    "win": 0.0001,
    "final": 0.0011,
    "sf": 0.0086,
    "qf": 0.0496,
    "win_lo": 0.0,
    "win_hi": 0.0008,
    "win_delta": -0.0024
  },
  "Canada": {
    "win": 0.0002,
    "final": 0.0014,
    "sf": 0.0093,
    "qf": 0.0507,
    "win_lo": 0.0,
    "win_hi": 0.0008,
    "win_delta": -0.0009
  },
  "Switzerland": {
    "win": 0.0154,
    "final": 0.0549,
    "sf": 0.1632,
    "qf": 0.3522,
    "win_lo": 0.0024,
    "win_hi": 0.0381,
    "win_delta": -0.0026
  },
  "Qatar": {
    "win": 0.0,
    "final": 0.0001,
    "sf": 0.0008,
    "qf": 0.0075,
    "win_lo": 0.0,
    "win_hi": 0.0,
    "win_delta": -0.0001
  },
  "Bosnia": {
    "win": 0.0,
    "final": 0.0002,
    "sf": 0.0021,
    "qf": 0.0169,
    "win_lo": 0.0,
    "win_hi": 0.0,
    "win_delta": -0.0001
  },
  "Brazil": {
    "win": 0.0341,
    "final": 0.0703,
    "sf": 0.2141,
    "qf": 0.3755,
    "win_lo": 0.0101,
    "win_hi": 0.0674,
    "win_delta": -0.0006
  },
  "Morocco": {
    "win": 0.0236,
    "final": 0.0539,
    "sf": 0.1603,
    "qf": 0.3386,
    "win_lo": 0.0084,
    "win_hi": 0.0492,
    "win_delta": -0.017
  },
  "Haiti": {
    "win": 0.0,
    "final": 0.0,
    "sf": 0.0001,
    "qf": 0.0004,
    "win_lo": 0.0,
    "win_hi": 0.0,
    "win_delta": 0.0
  },
  "Scotland": {
    "win": 0.0001,
    "final": 0.0007,
    "sf": 0.0051,
    "qf": 0.0288,
    "win_lo": 0.0,
    "win_hi": 0.0008,
    "win_delta": -0.0016
  },
  "USA": {
    "win": 0.0025,
    "final": 0.0122,
    "sf": 0.0429,
    "qf": 0.1356,
    "win_lo": 0.0,
    "win_hi": 0.0071,
    "win_delta": -0.0056
  },
  "Paraguay": {
    "win": 0.0006,
    "final": 0.0034,
    "sf": 0.0152,
    "qf": 0.0616,
    "win_lo": 0.0,
    "win_hi": 0.0016,
    "win_delta": -0.0026
  },
  "Australia": {
    "win": 0.0004,
    "final": 0.0021,
    "sf": 0.0101,
    "qf": 0.0415,
    "win_lo": 0.0,
    "win_hi": 0.0008,
    "win_delta": -0.0007
  },
  "Turkey": {
    "win": 0.0262,
    "final": 0.0771,
    "sf": 0.1767,
    "qf": 0.3489,
    "win_lo": 0.0047,
    "win_hi": 0.0542,
    "win_delta": -0.0097
  },
  "Germany": {
    "win": 0.0762,
    "final": 0.1816,
    "sf": 0.2956,
    "qf": 0.5528,
    "win_lo": 0.0379,
    "win_hi": 0.1153,
    "win_delta": -0.0018
  },
  "Curacao": {
    "win": 0.0,
    "final": 0.0,
    "sf": 0.0002,
    "qf": 0.0012,
    "win_lo": 0.0,
    "win_hi": 0.0,
    "win_delta": -0.0003
  },
  "Ivory Coast": {
    "win": 0.0023,
    "final": 0.0098,
    "sf": 0.0345,
    "qf": 0.1113,
    "win_lo": 0.0,
    "win_hi": 0.0063,
    "win_delta": -0.0071
  },
  "Ecuador": {
    "win": 0.0075,
    "final": 0.0243,
    "sf": 0.0686,
    "qf": 0.17,
    "win_lo": 0.0016,
    "win_hi": 0.0145,
    "win_delta": -0.0001
  },
  "Netherlands": {
    "win": 0.0092,
    "final": 0.0248,
    "sf": 0.1037,
    "qf": 0.2551,
    "win_lo": 0.0024,
    "win_hi": 0.0164,
    "win_delta": -0.0094
  },
  "Japan": {
    "win": 0.0152,
    "final": 0.0367,
    "sf": 0.1277,
    "qf": 0.2743,
    "win_lo": 0.0016,
    "win_hi": 0.0327,
    "win_delta": -0.0027
  },
  "Sweden": {
    "win": 0.0001,
    "final": 0.0007,
    "sf": 0.005,
    "qf": 0.0246,
    "win_lo": 0.0,
    "win_hi": 0.0,
    "win_delta": -0.0005
  },
  "Tunisia": {
    "win": 0.0,
    "final": 0.0,
    "sf": 0.0006,
    "qf": 0.0046,
    "win_lo": 0.0,
    "win_hi": 0.0,
    "win_delta": -0.0003
  },
  "Belgium": {
    "win": 0.0066,
    "final": 0.0243,
    "sf": 0.0705,
    "qf": 0.1864,
    "win_lo": 0.0008,
    "win_hi": 0.0144,
    "win_delta": -0.0034
  },
  "Egypt": {
    "win": 0.0011,
    "final": 0.0059,
    "sf": 0.0239,
    "qf": 0.0887,
    "win_lo": 0.0,
    "win_hi": 0.0031,
    "win_delta": -0.0068
  },
  "Iran": {
    "win": 0.0057,
    "final": 0.0209,
    "sf": 0.064,
    "qf": 0.1641,
    "win_lo": 0.0,
    "win_hi": 0.0161,
    "win_delta": -0.0043
  },
  "New Zealand": {
    "win": 0.0,
    "final": 0.0,
    "sf": 0.0,
    "qf": 0.0005,
    "win_lo": 0.0,
    "win_hi": 0.0,
    "win_delta": 0.0
  },
  "Spain": {
    "win": 0.2753,
    "final": 0.3648,
    "sf": 0.4653,
    "qf": 0.647,
    "win_lo": 0.1917,
    "win_hi": 0.358,
    "win_delta": 0.1102
  },
  "Cape Verde": {
    "win": 0.0002,
    "final": 0.0011,
    "sf": 0.0047,
    "qf": 0.024,
    "win_lo": 0.0,
    "win_hi": 0.0008,
    "win_delta": -0.0073
  },
  "Saudi Arabia": {
    "win": 0.0,
    "final": 0.0001,
    "sf": 0.0008,
    "qf": 0.0044,
    "win_lo": 0.0,
    "win_hi": 0.0,
    "win_delta": -0.0001
  },
  "Uruguay": {
    "win": 0.0049,
    "final": 0.0144,
    "sf": 0.0366,
    "qf": 0.1271,
    "win_lo": 0.0008,
    "win_hi": 0.0102,
    "win_delta": -0.005
  },
  "France": {
    "win": 0.1306,
    "final": 0.2423,
    "sf": 0.3841,
    "qf": 0.5487,
    "win_lo": 0.0859,
    "win_hi": 0.1749,
    "win_delta": 0.0526
  },
  "Senegal": {
    "win": 0.0103,
    "final": 0.0323,
    "sf": 0.0874,
    "qf": 0.19,
    "win_lo": 0.0008,
    "win_hi": 0.027,
    "win_delta": -0.0111
  },
  "Norway": {
    "win": 0.0643,
    "final": 0.1379,
    "sf": 0.2671,
    "qf": 0.4259,
    "win_lo": 0.0209,
    "win_hi": 0.1158,
    "win_delta": -0.0221
  },
  "Iraq": {
    "win": 0.0,
    "final": 0.0001,
    "sf": 0.0007,
    "qf": 0.0034,
    "win_lo": 0.0,
    "win_hi": 0.0,
    "win_delta": -0.0003
  },
  "Argentina": {
    "win": 0.149,
    "final": 0.225,
    "sf": 0.3201,
    "qf": 0.5838,
    "win_lo": 0.0781,
    "win_hi": 0.2233,
    "win_delta": 0.0396
  },
  "Algeria": {
    "win": 0.0063,
    "final": 0.0182,
    "sf": 0.0431,
    "qf": 0.1106,
    "win_lo": 0.0,
    "win_hi": 0.0155,
    "win_delta": -0.0101
  },
  "Austria": {
    "win": 0.0139,
    "final": 0.0338,
    "sf": 0.0724,
    "qf": 0.1978,
    "win_lo": 0.0009,
    "win_hi": 0.0263,
    "win_delta": -0.0252
  },
  "Jordan": {
    "win": 0.0,
    "final": 0.0,
    "sf": 0.0001,
    "qf": 0.0013,
    "win_lo": 0.0,
    "win_hi": 0.0,
    "win_delta": -0.0001
  },
  "Portugal": {
    "win": 0.0473,
    "final": 0.1184,
    "sf": 0.2445,
    "qf": 0.402,
    "win_lo": 0.0103,
    "win_hi": 0.0916,
    "win_delta": -0.0234
  },
  "DR Congo": {
    "win": 0.0012,
    "final": 0.0062,
    "sf": 0.022,
    "qf": 0.0662,
    "win_lo": 0.0,
    "win_hi": 0.0031,
    "win_delta": -0.0086
  },
  "Uzbekistan": {
    "win": 0.0002,
    "final": 0.0006,
    "sf": 0.0027,
    "qf": 0.0095,
    "win_lo": 0.0,
    "win_hi": 0.0,
    "win_delta": -0.0016
  },
  "Colombia": {
    "win": 0.0236,
    "final": 0.0686,
    "sf": 0.1627,
    "qf": 0.3063,
    "win_lo": 0.0068,
    "win_hi": 0.0454,
    "win_delta": -0.0007
  },
  "England": {
    "win": 0.0361,
    "final": 0.0917,
    "sf": 0.1563,
    "qf": 0.2853,
    "win_lo": 0.0159,
    "win_hi": 0.0571,
    "win_delta": 0.0006
  },
  "Croatia": {
    "win": 0.0041,
    "final": 0.015,
    "sf": 0.0404,
    "qf": 0.1073,
    "win_lo": 0.0,
    "win_hi": 0.0096,
    "win_delta": -0.0042
  },
  "Ghana": {
    "win": 0.0,
    "final": 0.0005,
    "sf": 0.0036,
    "qf": 0.0182,
    "win_lo": 0.0,
    "win_hi": 0.0,
    "win_delta": -0.0009
  },
  "Panama": {
    "win": 0.0,
    "final": 0.0,
    "sf": 0.0,
    "qf": 0.0002,
    "win_lo": 0.0,
    "win_hi": 0.0,
    "win_delta": 0.0
  }
}